extxyz-0.1.3.dist-info/METADATA
extxyz-0.1.3.dist-info/LICENSE
extxyz-0.1.3.dist-info/entry_points.txt
extxyz-0.1.3.dist-info/WHEEL
extxyz-0.1.3.dist-info/RECORD
extxyz-0.1.3.dist-info/top_level.txt
extxyz/_extxyz.so
extxyz/extxyz.py
extxyz/extxyz_kv_grammar.py
extxyz/cli.py
extxyz/utils.py
extxyz/__main__.py
extxyz/cextxyz.py
extxyz/__init__.py
extxyz.libs/libpcre2-8-9ebdaff2.so.0.5.0
