Metadata-Version: 2.1
Name: extxyz
Version: 0.1.3
Summary: UNKNOWN
Home-page: UNKNOWN
Author: various
License: UNKNOWN
Platform: UNKNOWN
License-File: LICENSE
Requires-Dist: numpy (>=1.13)
Requires-Dist: pyleri (>=1.3.3)
Requires-Dist: ase (>=3.17)
